pymetamodels/__init__.py
pymetamodels/obj_conf.py
pymetamodels/obj_data.py
pymetamodels/obj_logging.py
pymetamodels/obj_metamodel.py
pymetamodels/obj_optimization.py
pymetamodels/obj_plots.py
pymetamodels/obj_sampling_sensitivity.py
pymetamodels/pymeta_models.py
pymetamodels/clsxplots/__init__.py
pymetamodels/clsxplots/cls_2D_contour.py
pymetamodels/clsxplots/cls_3D_plot.py
pymetamodels/clsxplots/cls_bars.py
pymetamodels/clsxplots/clsxplots.py
pymetamodels/clsxplots/lib.py
pymetamodels/clsxplots/obj_func.py
pymetamodels-0.0.3.dist-info/LICENSE.md
pymetamodels-0.0.3.dist-info/METADATA
pymetamodels-0.0.3.dist-info/WHEEL
pymetamodels-0.0.3.dist-info/top_level.txt
pymetamodels-0.0.3.dist-info/zip-safe
pymetamodels-0.0.3.dist-info/RECORD
