Metadata-Version: 2.1
Name: pymetamodels
Version: 0.0.3
Summary: The pymetamodels package combines machine learning (ML) metamodeling and analysis tools for the virtual development of modeling systems within a common abstract framework implemented in an accessible and distributable Python package. This package is oriented to support ML applications in  material science, material informatics and the construction of materials, components and systems soft metamodels informed by hard physics-based modelling and experimental characterisations.
Home-page: https://github.com/ITAINNOVA/pymetamodels.git
Author: F Lahuerta
Author-email: flahuerta@itainnova.es
License: MIT
Keywords: pymetamodels,virtual,model,optimization,sensitivity,metamodeling,ML,mechanic,material,component,science
Classifier: Development Status :: 4 - Beta
Classifier: Environment :: Console
Classifier: Intended Audience :: Science/Research
Classifier: Programming Language :: Python :: 3
Classifier: License :: OSI Approved :: MIT License
Classifier: Natural Language :: English
Classifier: Natural Language :: Spanish
Classifier: Operating System :: Unix
Classifier: Operating System :: Microsoft :: Windows
Classifier: Topic :: Scientific/Engineering :: Physics
Classifier: Topic :: Scientific/Engineering :: Information Analysis
Requires-Python: >=3.7
License-File: LICENSE.md
Requires-Dist: numpy
Requires-Dist: scipy
Requires-Dist: scikit-learn
Requires-Dist: matplotlib
Requires-Dist: SALib
Requires-Dist: Pillow
Requires-Dist: xlrd
Requires-Dist: xlwt
Requires-Dist: xlutils
Requires-Dist: myst-parser
Requires-Dist: sphinxcontrib-bibtex
Requires-Dist: pybtex
Provides-Extra: docs
Requires-Dist: sphinx ; extra == 'docs'
Requires-Dist: myst-parser ; extra == 'docs'
Requires-Dist: sphinxcontrib-bibtex ; extra == 'docs'
